rdf2puml/__init__.py
rdf2puml/constants.py
rdf2puml/group.py
rdf2puml/pumlmodel.py
rdf2puml/rdf2puml.py
rdf2puml-1.2.0.data/scripts/rdf2puml
rdf2puml-1.2.0.dist-info/LICENSE
rdf2puml-1.2.0.dist-info/METADATA
rdf2puml-1.2.0.dist-info/WHEEL
rdf2puml-1.2.0.dist-info/top_level.txt
rdf2puml-1.2.0.dist-info/RECORD
