Metadata-Version: 2.1
Name: rdf2puml
Version: 1.2.0
Summary: Tool for Creating plantuml Files from rdf model.
Home-page: https://github.com/dfriedenberger/rdf2puml.git
Author: Dirk Friedenberger
Author-email: projekte@frittenburger.de
License: GPLv3
Classifier: Programming Language :: Python :: 3
Classifier: License :: OSI Approved :: GNU Lesser General Public License v3 (LGPLv3)
Classifier: Operating System :: OS Independent
License-File: LICENSE
Requires-Dist: rdflib
Requires-Dist: obse
